tests/parse/__init__.py
tests/parse/test_names.py
zavod/__init__.py
zavod/audit.py
zavod/cli.py
zavod/context.py
zavod/dataset.py
zavod/http.py
zavod/logs.py
zavod/py.typed
zavod/settings.py
zavod/util.py
zavod/parse/__init__.py
zavod/parse/addresses.py
zavod/parse/names.py
zavod/parse/xml.py
zavod/sinks/__init__.py
zavod/sinks/common.py
zavod/sinks/json_entity.py
zavod/sinks/statement.py
zavod-0.7.3.dist-info/LICENSE
zavod-0.7.3.dist-info/METADATA
zavod-0.7.3.dist-info/WHEEL
zavod-0.7.3.dist-info/entry_points.txt
zavod-0.7.3.dist-info/namespace_packages.txt
zavod-0.7.3.dist-info/top_level.txt
zavod-0.7.3.dist-info/RECORD
