Metadata-Version: 2.1
Name: zavod
Version: 0.7.3
Summary: Data factory for followthemoney data.
Home-page: https://github.com/opensanctions/zavod
Author: Friedrich Lindenberg
Author-email: friedrich@opensanctions.org
License: MIT
Keywords: data mapping identity followthemoney etl parsing
License-File: LICENSE
Requires-Dist: followthemoney (<4.0.0,>=3.2.0)
Requires-Dist: nomenklatura (<4.0.0,>=3.2.0)
Requires-Dist: addressformatting (<2.0.0,>=1.3.0)
Requires-Dist: datapatch (>=0.2.1)
Requires-Dist: click (<8.2.0,>=8.0.0)
Requires-Dist: requests
Requires-Dist: structlog
Requires-Dist: lxml
Provides-Extra: dev
Requires-Dist: wheel (>=0.29.0) ; extra == 'dev'
Requires-Dist: twine ; extra == 'dev'
Requires-Dist: mypy ; extra == 'dev'
Requires-Dist: flake8 (>=2.6.0) ; extra == 'dev'
Requires-Dist: pytest ; extra == 'dev'
Requires-Dist: pytest-cov ; extra == 'dev'
Requires-Dist: lxml-stubs ; extra == 'dev'
Requires-Dist: coverage (>=4.1) ; extra == 'dev'
Requires-Dist: types-setuptools ; extra == 'dev'
Requires-Dist: types-requests ; extra == 'dev'
